darksky_scraper
darksky_scraper/check_values
